rtl/riscv_defs.vh
// ============================================================
//  riscv_defs.vh  -  Definitii ISA pentru nucleul RV32IM
// ------------------------------------------------------------
//  Faza 1: opcode-uri, campuri funct3/funct7, encodarea ALU,
//  extensia M si extractoare de campuri din instructiune.
//  Toate sunt macro-uri de preprocesor => 100% sintetizabile.
// ============================================================
//  CONVENTII DE PROIECT (valabile in tot rtl/):
//    * RESET ACTIV PE 0 (active-low): semnal `rst_n`.
//        always @(posedge clk or negedge rst_n)
//          if (!rst_n) <reset> else <logica>
//    * Doar RTL SINTETIZABIL in rtl/ (fara #delay/initial de stare).
//    * Constructele de simulare stau exclusiv in test/.
// ============================================================

`ifndef RISCV_DEFS_VH
`define RISCV_DEFS_VH

// ------------------------------------------------------------
//  Parametri generali
// ------------------------------------------------------------
`define XLEN         32                 // latimea cuvantului
`define RV_NOP       32'h0000_0013      // addi x0, x0, 0  (bula in pipeline)
`define RESET_PC     32'h0000_0000      // adresa de start dupa reset

// ------------------------------------------------------------
//  Extractoare de campuri din instructiune (i = vector 32-bit)
//    Formate RISC-V:
//      R: funct7 | rs2 | rs1 | funct3 | rd | opcode
//      I: imm[11:0]       | rs1 | funct3 | rd | opcode
//      S: imm[11:5] | rs2 | rs1 | funct3 | imm[4:0] | opcode
//      B: imm[12|10:5]|rs2|rs1|funct3| imm[4:1|11] | opcode
//      U: imm[31:12]                  | rd | opcode
//      J: imm[20|10:1|11|19:12]       | rd | opcode
// ------------------------------------------------------------
`define OPCODE(i)    (i[6:0])
`define RD(i)        (i[11:7])
`define RS1(i)       (i[19:15])
`define RS2(i)       (i[24:20])
`define FUNCT3(i)    (i[14:12])
`define FUNCT7(i)    (i[31:25])

// ------------------------------------------------------------
//  Opcode-uri (bitii [6:0])
// ------------------------------------------------------------
`define OPC_LUI      7'b0110111         // U  - load upper immediate
`define OPC_AUIPC    7'b0010111         // U  - add upper imm to PC
`define OPC_JAL      7'b1101111         // J  - jump and link
`define OPC_JALR     7'b1100111         // I  - jump and link register
`define OPC_BRANCH   7'b1100011         // B  - branch conditionat
`define OPC_LOAD     7'b0000011         // I  - load din memorie
`define OPC_STORE    7'b0100011         // S  - store in memorie
`define OPC_OP_IMM   7'b0010011         // I  - ALU cu immediate
`define OPC_OP       7'b0110011         // R  - ALU cu registre (+ extensia M)
`define OPC_MISC_MEM 7'b0001111         // I  - FENCE
`define OPC_SYSTEM   7'b1110011         // I  - ECALL/EBREAK/CSR
`define OPC_AMO      7'b0101111         // A  - atomice (LR/SC/AMO)

//  Extensia A: funct3 = latime; aici doar word (.w)
`define F3_AMO_W     3'b010
//  funct5 = instr[31:27] (instr[31:25] fara aq/rl)
`define AMO_LR       5'b00010
`define AMO_SC       5'b00011
`define AMO_SWAP     5'b00001
`define AMO_ADD      5'b00000
`define AMO_XOR      5'b00100
`define AMO_AND      5'b01100
`define AMO_OR       5'b01000
`define AMO_MIN      5'b10000
`define AMO_MAX      5'b10100
`define AMO_MINU     5'b11000
`define AMO_MAXU     5'b11100

// ------------------------------------------------------------
//  funct3 pentru OP / OP-IMM (aritmetica/logica)
//    SUB vs ADD si SRA vs SRL se disting prin bitul funct7[5] (=i[30])
// ------------------------------------------------------------
`define F3_ADD_SUB   3'b000             // ADD/ADDI ; SUB (funct7[5]=1)
`define F3_SLL       3'b001             // shift left logic
`define F3_SLT       3'b010             // set less than (cu semn)
`define F3_SLTU      3'b011             // set less than (fara semn)
`define F3_XOR       3'b100
`define F3_SRL_SRA   3'b101             // SRL ; SRA (funct7[5]=1)
`define F3_OR        3'b110
`define F3_AND       3'b111

// ------------------------------------------------------------
//  funct3 pentru BRANCH
// ------------------------------------------------------------
`define F3_BEQ       3'b000
`define F3_BNE       3'b001
`define F3_BLT       3'b100
`define F3_BGE       3'b101
`define F3_BLTU      3'b110
`define F3_BGEU      3'b111

// ------------------------------------------------------------
//  funct3 pentru LOAD / STORE (dimensiunea accesului)
// ------------------------------------------------------------
`define F3_LB        3'b000             // load byte (cu semn)
`define F3_LH        3'b001             // load half (cu semn)
`define F3_LW        3'b010             // load word
`define F3_LBU       3'b100             // load byte (fara semn)
`define F3_LHU       3'b101             // load half (fara semn)

`define F3_SB        3'b000             // store byte
`define F3_SH        3'b001             // store half
`define F3_SW        3'b010             // store word

// ------------------------------------------------------------
//  funct7 relevante
// ------------------------------------------------------------
`define F7_BASE      7'b0000000         // ADD, SRL, AND, ...
`define F7_ALT       7'b0100000         // SUB, SRA  (bitul [5]=1)
`define F7_MULDIV    7'b0000001         // extensia M
`define F7_BIT5      30                 // pozitia bitului ALT in instructiune

// ------------------------------------------------------------
//  Extensia M (opcode OPC_OP, funct7 = F7_MULDIV), prin funct3
// ------------------------------------------------------------
`define F3_MUL       3'b000             // produs, 32 bitii inferiori
`define F3_MULH      3'b001             // produs sup., semnat x semnat
`define F3_MULHSU    3'b010             // produs sup., semnat x nesemnat
`define F3_MULHU     3'b011             // produs sup., nesemnat x nesemnat
`define F3_DIV       3'b100             // impartire cu semn
`define F3_DIVU      3'b101             // impartire fara semn
`define F3_REM       3'b110             // rest cu semn
`define F3_REMU      3'b111             // rest fara semn

// ------------------------------------------------------------
//  funct3 pentru SYSTEM (ECALL/EBREAK + CSR)
// ------------------------------------------------------------
`define F3_PRIV      3'b000             // ECALL/EBREAK (dupa funct12)
`define F3_CSRRW     3'b001
`define F3_CSRRS     3'b010
`define F3_CSRRC     3'b011
`define F3_CSRRWI    3'b101
`define F3_CSRRSI    3'b110
`define F3_CSRRCI    3'b111

// ------------------------------------------------------------
//  funct12 (instr[31:20]) pentru SYSTEM cu funct3=000
// ------------------------------------------------------------
`define SYS_ECALL    12'h000
`define SYS_EBREAK   12'h001
`define SYS_MRET     12'h302
`define SYS_SRET     12'h102
`define SYS_WFI      12'h105

// ------------------------------------------------------------
//  Adrese CSR (mod masina) - subset minim pentru Zicsr + trap
// ------------------------------------------------------------
`define CSR_MSTATUS  12'h300
`define CSR_MISA     12'h301
`define CSR_MIE      12'h304
`define CSR_MTVEC    12'h305
`define CSR_MSCRATCH 12'h340
`define CSR_MEPC     12'h341
`define CSR_MCAUSE   12'h342
`define CSR_MTVAL    12'h343
`define CSR_MIP      12'h344
`define CSR_MVENDORID 12'hF11
`define CSR_MARCHID   12'hF12
`define CSR_MIMPID    12'hF13
`define CSR_MHARTID   12'hF14

`define CSR_MEDELEG  12'h302
`define CSR_MIDELEG  12'h303
`define CSR_SSTATUS  12'h100
`define CSR_SIE      12'h104
`define CSR_STVEC    12'h105
`define CSR_SSCRATCH 12'h140
`define CSR_SEPC     12'h141
`define CSR_SCAUSE   12'h142
`define CSR_STVAL    12'h143
`define CSR_SIP      12'h144
`define CSR_SATP     12'h180

`define PRIV_U       2'b00
`define PRIV_S       2'b01
`define PRIV_M       2'b11

`define CLINT_HI     16'h0200

//  misa pentru RV32IM: MXL=01 (32b) | I (bit8) | M (bit12)
`define MISA_RV32IM  32'h40001100

// ------------------------------------------------------------
//  Cauze de trap (mcause, bitul de interrupt = 0 pentru exceptii)
// ------------------------------------------------------------
`define MISA_RV32IMA 32'h40141101

`define CAUSE_INSTR_MISALIGN 32'd0
`define CAUSE_ILLEGAL    32'd2
`define CAUSE_BREAKPOINT 32'd3
`define CAUSE_LOAD_MISALIGN  32'd4
`define CAUSE_STORE_MISALIGN 32'd6
`define CAUSE_ECALL_U    32'd8
`define CAUSE_ECALL_S    32'd9
`define CAUSE_ECALL_M    32'd11
`define CAUSE_INSTR_PAGE 32'd12
`define CAUSE_LOAD_PAGE  32'd13
`define CAUSE_STORE_PAGE 32'd15

// ------------------------------------------------------------
//  Encodarea interna a operatiei ALU (semnal de control, 4 biti)
//    Nu face parte din ISA - e conventia noastra interna.
// ------------------------------------------------------------
`define ALU_OP_W     4
`define ALU_ADD      4'b0000
`define ALU_SUB      4'b0001
`define ALU_SLL      4'b0010
`define ALU_SLT      4'b0011            // set-less-than cu semn
`define ALU_SLTU     4'b0100            // set-less-than fara semn
`define ALU_XOR      4'b0101
`define ALU_SRL      4'b0110
`define ALU_SRA      4'b0111
`define ALU_OR       4'b1000
`define ALU_AND      4'b1001
`define ALU_COPY_B   4'b1010            // trece operandul B (pentru LUI)
`define ALU_NOP      4'b1111            // fara efect (bula)

// ------------------------------------------------------------
//  Selectorul de tip immediate (semnal de control, intern)
//    Spune lui imm_gen din ce format sa extraga immediate-ul.
// ------------------------------------------------------------
`define IMM_SEL_W    3
`define IMM_I        3'd0               // OP-IMM, LOAD, JALR
`define IMM_S        3'd1               // STORE
`define IMM_B        3'd2               // BRANCH
`define IMM_U        3'd3               // LUI, AUIPC
`define IMM_J        3'd4               // JAL
`define IMM_ZERO     3'd5               // immediate = 0 (adresa atomicelor = rs1+0)

// ------------------------------------------------------------
//  Selectorul sursei de writeback (ce se scrie in registrul rd)
// ------------------------------------------------------------
`define WB_SEL_W     2
`define WB_ALU       2'd0               // rezultatul ALU
`define WB_MEM       2'd1               // data citita din memorie (load)
`define WB_PC4       2'd2               // PC+4 (adresa de retur, jal/jalr)

// ------------------------------------------------------------
//  Coduri pentru unitatea de forwarding (Faza 4)
//    Selecteaza sursa operandului ALU in etapa EX.
// ------------------------------------------------------------
`define FWD_NONE     2'b00              // din ID/EX (register file)
`define FWD_EXMEM    2'b10              // din EX/MEM (instr. precedenta)
`define FWD_MEMWB    2'b01              // din MEM/WB (cu 2 instr. inainte)

`endif  // RISCV_DEFS_VH

rtl/mmu.v
`timescale 1ns / 1ps
`include "riscv_defs.vh"

module mmu (
    input  wire        clk,
    input  wire        rst_n,

    input  wire        req,
    input  wire [31:0] vaddr,
    input  wire [1:0]  access,
    input  wire [31:0] satp,
    input  wire [1:0]  priv,
    input  wire        sum,
    input  wire        mxr,
    input  wire        flush,

    output reg         done,
    output reg  [31:0] paddr,
    output reg         fault,
    output reg  [3:0]  fault_cause,
    output reg  [31:0] leaf_pte,

    output reg         mem_req,
    output reg  [31:0] mem_addr,
    input  wire [31:0] mem_rdata,
    input  wire        mem_ack
);
    localparam TLBN = 8;
    localparam S_IDLE = 2'd0, S_L1 = 2'd1, S_L0 = 2'd2, S_DONE = 2'd3;
    reg [1:0]  state;
    reg [31:0] vaddr_q;
    reg [1:0]  access_q;

    reg        tlb_v   [0:TLBN-1];
    reg [19:0] tlb_tag [0:TLBN-1];
    reg [31:0] tlb_pte [0:TLBN-1];
    reg        tlb_sup [0:TLBN-1];
    reg [2:0]  rr;
    integer    i;

    function [3:0] pf_cause(input [1:0] acc);
        case (acc)
            2'd0:    pf_cause = 4'd12;
            2'd1:    pf_cause = 4'd13;
            default: pf_cause = 4'd15;
        endcase
    endfunction

    function bad_leaf(input [31:0] p, input [1:0] acc);
        reg ok;
        reg r, w, x, u, a, d;
        begin
            r=p[1]; w=p[2]; x=p[3]; u=p[4]; a=p[6]; d=p[7];
            if      (acc == 2'd0) ok = x;
            else if (acc == 2'd1) ok = r | (mxr & x);
            else                  ok = w;
            if (priv == `PRIV_U && !u)                       ok = 1'b0;
            if (priv == `PRIV_S &&  u && acc != 2'd0 && !sum) ok = 1'b0;
            if (priv == `PRIV_S &&  u && acc == 2'd0)         ok = 1'b0;
            if (!a)                                          ok = 1'b0;
            if (acc == 2'd2 && !d)                           ok = 1'b0;
            bad_leaf = ~ok;
        end
    endfunction

    // cautare asociativa in TLB pe adresa ceruta
    reg        hit;
    reg [2:0]  hidx;
    reg [31:0] hit_pte;
    reg        hit_sup;
    always @* begin
        hit = 1'b0; hidx = 3'd0; hit_pte = 32'b0; hit_sup = 1'b0;
        for (i = 0; i < TLBN; i = i + 1)
            if (tlb_v[i] && (tlb_sup[i] ? (tlb_tag[i][19:10] == vaddr[31:22])
                                        : (tlb_tag[i] == vaddr[31:12]))) begin
                hit = 1'b1; hidx = i[2:0]; hit_pte = tlb_pte[i]; hit_sup = tlb_sup[i];
            end
    end
    wire [31:0] hit_paddr = hit_sup ? {hit_pte[29:20], vaddr[21:0]}
                                    : {hit_pte[29:10], vaddr[11:0]};

    wire l1_invalid = !mem_rdata[0] || (!mem_rdata[1] && mem_rdata[2]);
    wire l1_leaf    =  mem_rdata[1] || mem_rdata[3];
    wire l0_invalid = !mem_rdata[0] || (!mem_rdata[1] && mem_rdata[2])
                    || !(mem_rdata[1] || mem_rdata[3]);

    always @(posedge clk or negedge rst_n) begin
        if (!rst_n) begin
            state <= S_IDLE; done <= 1'b0; fault <= 1'b0;
            mem_req <= 1'b0; paddr <= 32'b0; fault_cause <= 4'b0;
            rr <= 3'b0;
            for (i = 0; i < TLBN; i = i + 1) tlb_v[i] <= 1'b0;
        end else begin
            done <= 1'b0; fault <= 1'b0;
            if (flush) for (i = 0; i < TLBN; i = i + 1) tlb_v[i] <= 1'b0;
            case (state)
                S_IDLE: if (req) begin
                    vaddr_q  <= vaddr;
                    access_q <= access;
                    if (hit) begin
                        paddr       <= hit_paddr;
                        fault       <= bad_leaf(hit_pte, access);
                        fault_cause <= pf_cause(access);
                        leaf_pte    <= hit_pte;
                        done        <= 1'b1;
                        state       <= S_DONE;
                    end else begin
                        mem_addr <= {satp[21:0], 12'b0} + {20'b0, vaddr[31:22], 2'b0};
                        mem_req  <= 1'b1;
                        state    <= S_L1;
                    end
                end
                S_L1: if (mem_ack) begin
                    mem_req <= 1'b0;
                    if (l1_invalid) begin
                        fault <= 1'b1; fault_cause <= pf_cause(access_q);
                        done  <= 1'b1; state <= S_DONE;
                    end else if (l1_leaf) begin
                        done <= 1'b1; state <= S_DONE;
                        fault <= (mem_rdata[19:10] != 10'b0) | bad_leaf(mem_rdata, access_q);
                        fault_cause <= pf_cause(access_q);
                        paddr <= {mem_rdata[29:20], vaddr_q[21:0]};
                        leaf_pte <= mem_rdata;
                        if (!((mem_rdata[19:10] != 10'b0) | bad_leaf(mem_rdata, access_q)) & ~flush) begin
                            tlb_v[rr]   <= 1'b1; tlb_tag[rr] <= vaddr_q[31:12];
                            tlb_pte[rr] <= mem_rdata; tlb_sup[rr] <= 1'b1;
                            rr <= rr + 3'd1;
                        end
                    end else begin
                        mem_addr <= {mem_rdata[31:10], 12'b0} + {20'b0, vaddr_q[21:12], 2'b0};
                        mem_req  <= 1'b1;
                        state    <= S_L0;
                    end
                end
                S_L0: if (mem_ack) begin
                    mem_req <= 1'b0;
                    done <= 1'b1; state <= S_DONE;
                    fault <= l0_invalid | bad_leaf(mem_rdata, access_q);
                    fault_cause <= pf_cause(access_q);
                    paddr <= {mem_rdata[29:10], vaddr_q[11:0]};
                    leaf_pte <= mem_rdata;
                    if (!(l0_invalid | bad_leaf(mem_rdata, access_q)) & ~flush) begin
                        tlb_v[rr]   <= 1'b1; tlb_tag[rr] <= vaddr_q[31:12];
                        tlb_pte[rr] <= mem_rdata; tlb_sup[rr] <= 1'b0;
                        rr <= rr + 3'd1;
                    end
                end
                S_DONE: state <= S_IDLE;
                default: state <= S_IDLE;
            endcase
        end
    end
endmodule

test/tb_mmu.v
`timescale 1ns / 1ps
`include "riscv_defs.vh"

`ifndef DUMP_FILE
 `define DUMP_FILE "waveform/tb_mmu.vcd"
`endif

module tb_mmu;
    reg         clk = 0, rst_n;
    reg         req;
    reg  [31:0] vaddr, satp;
    reg  [1:0]  access, priv;
    reg         sum, mxr;
    wire        done, fault;
    wire [31:0] paddr;
    wire [3:0]  fault_cause;

    wire        mem_req;
    wire [31:0] mem_addr;
    reg  [31:0] pmem [0:16383];
    wire [31:0] mem_rdata = pmem[mem_addr[15:2]];
    wire        mem_ack   = mem_req;

    integer errors = 0;
    always #5 clk = ~clk;

    mmu dut (.clk(clk), .rst_n(rst_n), .req(req), .vaddr(vaddr), .access(access),
             .satp(satp), .priv(priv), .sum(sum), .mxr(mxr), .flush(1'b0),
             .done(done), .paddr(paddr), .fault(fault), .fault_cause(fault_cause),
             .mem_req(mem_req), .mem_addr(mem_addr), .mem_rdata(mem_rdata), .mem_ack(mem_ack));

    task xlate;
        input [31:0] va;
        input [1:0]  acc;
        begin
            @(negedge clk); req=1; vaddr=va; access=acc;
            @(negedge clk); req=0;
            while (!done) @(negedge clk);
        end
    endtask

    task chk;
        input integer id;
        input [31:0] got, exp;
        begin
            if (got !== exp) begin
                errors=errors+1;
                $display("  FAIL %0d: got=%h exp=%h", id, got, exp);
            end
        end
    endtask

    integer i;
    initial begin
        $dumpfile(`DUMP_FILE); $dumpvars(0, tb_mmu);
        for (i=0;i<16384;i=i+1) pmem[i]=32'b0;

        // tabel nivel 1 la 0x1000 (PPN=1): intrarea VPN1=1 -> pointer la tabel nivel 0 (PPN=2)
        pmem[32'h1004>>2] = (32'd2 << 10) | 32'h001;          // pointer, V
        // intrarea VPN1=2 ramane 0 (invalida)

        // tabel nivel 0 la 0x2000 (PPN=2)
        pmem[32'h2000>>2] = (32'd5 << 10) | 32'h0DF;          // frunza PPN=5, V|R|W|X|U|A|D
        pmem[32'h2004>>2] = (32'd6 << 10) | 32'h05B;          // frunza PPN=6, V|R|X|U|A (fara W)

        satp = 32'h8000_0001;  // MODE=1, root PPN=1
        priv = `PRIV_U; sum=0; mxr=0; req=0; access=0; vaddr=0;
        rst_n=0; @(negedge clk); @(negedge clk); rst_n=1;

        // 1) traducere load reusita: VA 0x00400ABC -> PA 0x5ABC
        xlate(32'h0040_0ABC, 2'd1);
        chk(1, {31'b0, fault}, 32'b0);
        chk(2, paddr, 32'h0000_5ABC);

        // 2) store pe pagina fara W -> store page fault (cauza 15)
        xlate(32'h0040_1000, 2'd2);
        chk(3, {31'b0, fault}, 32'b1);
        chk(4, {28'b0, fault_cause}, 32'd15);

        // 3) load pe aceeasi pagina (are R) -> PA 0x6000
        xlate(32'h0040_1000, 2'd1);
        chk(5, {31'b0, fault}, 32'b0);
        chk(6, paddr, 32'h0000_6000);

        // 4) VA cu intrare nivel 1 invalida -> load page fault (cauza 13)
        xlate(32'h0080_0000, 2'd1);
        chk(7, {31'b0, fault}, 32'b1);
        chk(8, {28'b0, fault_cause}, 32'd13);

        // 5) fetch pe pagina fara X (frunza PPN=5 are X, deci testez pe pagina R/X) -> ok
        xlate(32'h0040_1000, 2'd0);
        chk(9, {31'b0, fault}, 32'b0);
        chk(10, paddr, 32'h0000_6000);

        if (errors==0) $display("[MMU] >>> PASS <<< (traducere Sv32 + page fault)");
        else           $display("[MMU] >>> FAIL <<< (%0d erori)", errors);
        $finish;
    end
endmodule

waveform/tb_mmu.vcd
$date
	Sun Jun 14 15:37:49 2026
$end
$version
	Icarus Verilog
$end
$timescale
	1ps
$end
$scope module tb_mmu $end
$var wire 1 ! mem_ack $end
$var wire 32 " mem_rdata [31:0] $end
$var wire 32 # paddr [31:0] $end
$var wire 1 $ mem_req $end
$var wire 32 % mem_addr [31:0] $end
$var wire 4 & fault_cause [3:0] $end
$var wire 1 ' fault $end
$var wire 1 ( done $end
$var reg 2 ) access [1:0] $end
$var reg 1 * clk $end
$var reg 1 + mxr $end
$var reg 2 , priv [1:0] $end
$var reg 1 - req $end
$var reg 1 . rst_n $end
$var reg 32 / satp [31:0] $end
$var reg 1 0 sum $end
$var reg 32 1 vaddr [31:0] $end
$var integer 32 2 errors [31:0] $end
$var integer 32 3 i [31:0] $end
$scope module dut $end
$var wire 2 4 access [1:0] $end
$var wire 1 * clk $end
$var wire 1 5 flush $end
$var wire 1 6 l0_invalid $end
$var wire 1 7 l1_invalid $end
$var wire 1 8 l1_leaf $end
$var wire 1 ! mem_ack $end
$var wire 32 9 mem_rdata [31:0] $end
$var wire 1 + mxr $end
$var wire 2 : priv [1:0] $end
$var wire 1 - req $end
$var wire 1 . rst_n $end
$var wire 32 ; satp [31:0] $end
$var wire 1 0 sum $end
$var wire 32 < vaddr [31:0] $end
$var wire 32 = hit_paddr [31:0] $end
$var parameter 2 > S_DONE $end
$var parameter 2 ? S_IDLE $end
$var parameter 2 @ S_L0 $end
$var parameter 2 A S_L1 $end
$var parameter 32 B TLBN $end
$var reg 2 C access_q [1:0] $end
$var reg 1 ( done $end
$var reg 1 ' fault $end
$var reg 4 D fault_cause [3:0] $end
$var reg 3 E hidx [2:0] $end
$var reg 1 F hit $end
$var reg 32 G hit_pte [31:0] $end
$var reg 1 H hit_sup $end
$var reg 32 I leaf_pte [31:0] $end
$var reg 32 J mem_addr [31:0] $end
$var reg 1 $ mem_req $end
$var reg 32 K paddr [31:0] $end
$var reg 3 L rr [2:0] $end
$var reg 2 M state [1:0] $end
$var reg 32 N vaddr_q [31:0] $end
$var integer 32 O i [31:0] $end
$scope function bad_leaf $end
$var reg 1 P a $end
$var reg 2 Q acc [1:0] $end
$var reg 1 R d $end
$var reg 1 S ok $end
$var reg 32 T p [31:0] $end
$var reg 1 U r $end
$var reg 1 V u $end
$var reg 1 W w $end
$var reg 1 X x $end
$upscope $end
$scope function pf_cause $end
$var reg 2 Y acc [1:0] $end
$upscope $end
$upscope $end
$scope task chk $end
$var reg 32 Z exp [31:0] $end
$var reg 32 [ got [31:0] $end
$var integer 32 \ id [31:0] $end
$upscope $end
$scope task xlate $end
$var reg 2 ] acc [1:0] $end
$var reg 32 ^ va [31:0] $end
$upscope $end
$upscope $end
$enddefinitions $end
$comment Show the parameter values. $end
$dumpall
b1000 B
b1 A
b10 @
b0 ?
b11 >
$end
#0
$dumpvars
bx ^
bx ]
bx \
bx [
bx Z
bx Y
xX
xW
xV
xU
bx T
xS
xR
bx Q
xP
b1000 O
bx N
b0 M
b0 L
b0 K
bx J
bx I
0H
b0 G
0F
b0 E
b0 D
bx C
b0 =
b0 <
b10000000000000000000000000000001 ;
b0 :
bx 9
x8
x7
x6
05
b0 4
b100000000000000 3
b0 2
b0 1
00
b10000000000000000000000000000001 /
0.
0-
b0 ,
0+
0*
b0 )
0(
0'
b0 &
bx %
0$
b0 #
bx "
0!
$end
#5000
b1000 O
1*
#10000
0*
#15000
b1000 O
1*
#20000
b1 ]
b10000000000101010111100 ^
1.
0*
#25000
1*
#30000
b101010111100 =
b1000 O
b1 )
b1 4
b10000000000101010111100 1
b10000000000101010111100 <
1-
0*
#35000
16
07
08
b100000000001 "
b100000000001 9
b1 M
1!
1$
b1000000000100 %
b1000000000100 J
b1 C
b10000000000101010111100 N
1*
#40000
0-
0*
#45000
06
18
b1010011011111 "
b1010011011111 9
b10 M
b10000000000000 %
b10000000000000 J
1!
1$
1*
#50000
0*
#55000
b101101010111100 =
b1010011011111 G
1F
b1000 O
b1 L
b1010011011111 I
b101101010111100 #
b101101010111100 K
b1101 &
b1101 D
b11 M
1(
0!
0$
b1 Y
1S
1R
1P
1V
1X
1W
1U
b1010011011111 T
b1 Q
1*
#60000
b10 ]
b10000000001000000000000 ^
b101101010111100 Z
b101101010111100 [
b10 \
0*
#65000
b0 M
0(
1*
#70000
b0 =
b1000 O
b0 G
0F
b10 )
b10 4
b10000000001000000000000 1
b10000000001000000000000 <
1-
0*
#75000
16
08
b100000000001 "
b100000000001 9
b1 M
1!
1$
b1000000000100 %
b1000000000100 J
b10 C
b10000000001000000000000 N
1*
#80000
0-
0*
#85000
06
18
b1100001011011 "
b1100001011011 9
b10 M
b10000000000100 %
b10000000000100 J
1!
1$
1*
#90000
0*
#95000
b1100001011011 I
b110000000000000 #
b110000000000000 K
b1111 &
b1111 D
1'
b11 M
1(
0!
0$
b10 Y
0S
0R
0W
b1100001011011 T
b10 Q
1*
#100000
b1 ]
b1111 Z
b1111 [
b100 \
0*
#105000
b0 M
0'
0(
1*
#110000
b1 )
b1 4
1-
0*
#115000
16
08
b100000000001 "
b100000000001 9
b1 M
1!
1$
b1000000000100 %
b1000000000100 J
b1 C
1*
#120000
0-
0*
#125000
06
18
b1100001011011 "
b1100001011011 9
b10 M
b10000000000100 %
b10000000000100 J
1!
1$
1*
#130000
0*
#135000
b110000000000000 =
b1100001011011 G
b1 E
1F
b1000 O
b10 L
b1101 &
b1101 D
b11 M
1(
0!
0$
b1 Y
1S
b1 Q
1*
#140000
b100000000000000000000000 ^
b110000000000000 Z
b110000000000000 [
b110 \
0*
#145000
b0 M
0(
1*
#150000
b0 =
b1000 O
b0 G
b0 E
0F
b100000000000000000000000 1
b100000000000000000000000 <
1-
0*
#155000
16
17
08
b0 "
b0 9
b1 M
1!
1$
b1000000001000 %
b1000000001000 J
b100000000000000000000000 N
1*
#160000
0-
0*
#165000
b11 M
1(
1'
0!
0$
1*
#170000
b0 ]
b10000000001000000000000 ^
b1101 Z
b1101 [
b1000 \
0*
#175000
b0 M
0'
0(
1*
#180000
b110000000000000 =
b1100001011011 G
b1 E
1F
b1000 O
b0 )
b0 4
b10000000001000000000000 1
b10000000001000000000000 <
1-
0*
#185000
b11 M
1(
b1100 &
b1100 D
b0 C
b10000000001000000000000 N
b0 Y
b0 Q
1*
#190000
b110000000000000 Z
b110000000000000 [
b1010 \
0-
0*
