rtl/plic.v
`timescale 1ns / 1ps

// PLIC minimal: N surse (id 1..N), un singur context (M-mode, hart 0).
// Harta (offset fata de baza, stil standard):
//   0x000004 + 4*(id-1) : prioritate sursa id   (3 biti)
//   0x001000            : pending (read-only, bit/sursa)
//   0x002000            : enable context 0       (bit/sursa)
//   0x200000            : threshold context 0
//   0x200004            : claim (citire) / complete (scriere)
module plic #(parameter integer N = 4) (
    input  wire        clk,
    input  wire        rst_n,
    input  wire        sel,
    input  wire        we,
    input  wire [23:0] off,
    input  wire [31:0] wdata,
    output reg  [31:0] rdata,

    input  wire [N:1]  src,
    output wire        meip
);
    localparam [23:0] O_PENDING = 24'h001000;
    localparam [23:0] O_ENABLE  = 24'h002000;
    localparam [23:0] O_THRESH  = 24'h200000;
    localparam [23:0] O_CLAIM   = 24'h200004;

    reg [2:0]  prio [1:N];
    reg [N:1]  ip;
    reg [N:1]  enable;
    reg [N:1]  inservice;
    reg [2:0]  threshold;
    integer    i;

    // selectie: cea mai mare prioritate printre sursele pending+enabled peste prag
    reg [2:0] best_id, best_pri;
    always @* begin
        best_id = 3'd0; best_pri = 3'd0;
        for (i = 1; i <= N; i = i + 1)
            if (ip[i] & enable[i] & (prio[i] > threshold) & (prio[i] > best_pri)) begin
                best_pri = prio[i];
                best_id  = i[2:0];
            end
    end
    assign meip = (best_id != 3'd0);

    wire prio_acc = sel & (off >= 24'h000004) & (off <= (24'h000004 + 4*(N-1)));
    wire [31:0] prio_id = (off - 24'h000004) >> 2;   // 0..N-1

    always @* begin
        rdata = 32'b0;
        if (prio_acc)               rdata = {29'b0, prio[prio_id[2:0] + 1]};
        else if (off == O_PENDING)  rdata = {{(32-N){1'b0}}, ip, 1'b0};
        else if (off == O_ENABLE)   rdata = {{(32-N){1'b0}}, enable, 1'b0};
        else if (off == O_THRESH)   rdata = {29'b0, threshold};
        else if (off == O_CLAIM)    rdata = {29'b0, best_id};
    end

    always @(posedge clk or negedge rst_n) begin
        if (!rst_n) begin
            ip <= 0; enable <= 0; inservice <= 0; threshold <= 3'b0;
            for (i = 1; i <= N; i = i + 1) prio[i] <= 3'b0;
        end else begin
            // gateway: ridica pending cat timp sursa e activa si nu e in tratare
            for (i = 1; i <= N; i = i + 1)
                if (src[i] & ~inservice[i]) ip[i] <= 1'b1;

            if (sel & we) begin
                if (prio_acc)              prio[prio_id[2:0] + 1] <= wdata[2:0];
                else if (off == O_ENABLE)  enable    <= wdata[N:1];
                else if (off == O_THRESH)  threshold <= wdata[2:0];
                else if (off == O_CLAIM)   inservice[wdata[2:0]] <= 1'b0;   // complete
            end

            // claim (citire): preia sursa, sterge pending, marcheaza in tratare
            if (sel & ~we & (off == O_CLAIM) & (best_id != 3'd0)) begin
                ip[best_id]        <= 1'b0;
                inservice[best_id] <= 1'b1;
            end
        end
    end
endmodule

test/tb_plic.v
`timescale 1ns / 1ps

`ifndef DUMP_FILE
 `define DUMP_FILE "waveform/tb_plic.vcd"
`endif

module tb_plic;
    localparam N = 4;
    reg         clk=0, rst_n;
    reg         sel, we;
    reg  [23:0] off;
    reg  [31:0] wdata;
    wire [31:0] rdata;
    reg  [N:1]  src;
    wire        meip;
    integer     errors=0;

    always #5 clk=~clk;

    plic #(.N(N)) dut (
        .clk(clk), .rst_n(rst_n), .sel(sel), .we(we),
        .off(off), .wdata(wdata), .rdata(rdata), .src(src), .meip(meip)
    );

    task pwrite;
        input [23:0] o; input [31:0] d;
        begin @(negedge clk); sel=1; we=1; off=o; wdata=d; @(negedge clk); sel=0; we=0; end
    endtask

    task pclaim;            // citire claim cu efect (sterge pending)
        output [31:0] d;
        begin
            @(negedge clk); sel=1; we=0; off=24'h200004;
            #1 d=rdata;                 // lasa combinational sa se aseze
            @(negedge clk); sel=0;
        end
    endtask

    task chk;
        input integer id; input [31:0] got, exp;
        begin
            if (got !== exp) begin
                errors=errors+1; $display("  FAIL %0d: got=%h exp=%h", id, got, exp);
            end
        end
    endtask

    reg [31:0] c;
    initial begin
        $dumpfile(`DUMP_FILE); $dumpvars(0, tb_plic);
        sel=0; we=0; off=0; wdata=0; src=0;
        rst_n=0; repeat(3) @(negedge clk); rst_n=1; @(negedge clk);

        // prioritati: src1=1, src2=2, src3=3, src4=1
        pwrite(24'h000004, 1); pwrite(24'h000008, 2);
        pwrite(24'h00000C, 3); pwrite(24'h000010, 1);
        pwrite(24'h002000, 32'h0000_001E);   // enable src1..4
        pwrite(24'h200000, 0);                // threshold 0

        // Test 1: o sursa
        src=4'b0001; @(negedge clk); @(negedge clk);
        chk(1, {31'b0, meip}, 1);             // meip ridicat
        pclaim(c); chk(2, c, 1);              // claim -> sursa 1
        @(negedge clk);
        chk(3, {31'b0, meip}, 0);             // pending sters
        pwrite(24'h200004, 1);                // complete 1
        src=0; @(negedge clk);

        // Test 2: prioritate (src1+src2 -> intai 2, apoi 1)
        src=4'b0011; @(negedge clk); @(negedge clk);
        pclaim(c); chk(4, c, 2);              // prioritatea mai mare castiga
        @(negedge clk);
        pclaim(c); chk(5, c, 1);
        pwrite(24'h200004, 2); pwrite(24'h200004, 1);
        src=0; @(negedge clk);

        // Test 3: threshold (prag 2: src1 mascat, src3 trece)
        pwrite(24'h200000, 2);
        src=4'b0001; @(negedge clk); @(negedge clk);
        chk(6, {31'b0, meip}, 0);             // prio 1 nu > 2
        src=4'b0100; @(negedge clk); @(negedge clk);
        chk(7, {31'b0, meip}, 1);             // prio 3 > 2
        pclaim(c); chk(8, c, 3);

        if (errors==0) $display("[PLIC] >>> PASS <<< (prioritati + threshold + claim/complete)");
        else           $display("[PLIC] >>> FAIL <<< (%0d erori)", errors);
        $finish;
    end
endmodule

waveform/tb_plic.vcd
$date
	Sun Jun 14 20:18:14 2026
$end
$version
	Icarus Verilog
$end
$timescale
	1ps
$end
$scope module tb_plic $end
$var wire 32 ! rdata [31:0] $end
$var wire 1 " meip $end
$var parameter 32 # N $end
$var reg 32 $ c [31:0] $end
$var reg 1 % clk $end
$var reg 24 & off [23:0] $end
$var reg 1 ' rst_n $end
$var reg 1 ( sel $end
$var reg 4 ) src [4:1] $end
$var reg 32 * wdata [31:0] $end
$var reg 1 + we $end
$var integer 32 , errors [31:0] $end
$scope module dut $end
$var wire 1 % clk $end
$var wire 24 - off [23:0] $end
$var wire 1 . prio_acc $end
$var wire 1 ' rst_n $end
$var wire 1 ( sel $end
$var wire 4 / src [4:1] $end
$var wire 32 0 wdata [31:0] $end
$var wire 1 + we $end
$var wire 32 1 prio_id [31:0] $end
$var wire 1 " meip $end
$var parameter 32 2 N $end
$var parameter 24 3 O_CLAIM $end
$var parameter 24 4 O_ENABLE $end
$var parameter 24 5 O_PENDING $end
$var parameter 24 6 O_THRESH $end
$var reg 3 7 best_id [2:0] $end
$var reg 3 8 best_pri [2:0] $end
$var reg 4 9 enable [4:1] $end
$var reg 4 : inservice [4:1] $end
$var reg 4 ; ip [4:1] $end
$var reg 32 < rdata [31:0] $end
$var reg 3 = threshold [2:0] $end
$var integer 32 > i [31:0] $end
$upscope $end
$scope task chk $end
$var reg 32 ? exp [31:0] $end
$var reg 32 @ got [31:0] $end
$var integer 32 A id [31:0] $end
$upscope $end
$scope task pclaim $end
$var reg 32 B d [31:0] $end
$upscope $end
$scope task pwrite $end
$var reg 32 C d [31:0] $end
$var reg 24 D o [23:0] $end
$upscope $end
$upscope $end
$enddefinitions $end
$comment Show the parameter values. $end
$dumpall
b1000000000000000000000 6
b1000000000000 5
b10000000000000 4
b1000000000000000000100 3
b100 2
b100 #
$end
#0
$dumpvars
bx D
bx C
bx B
bx A
bx @
bx ?
b101 >
b0 =
b0 <
b0 ;
b0 :
b0 9
b0 8
b0 7
b111111111111111111111111111111 1
b0 0
b0 /
0.
b0 -
b0 ,
0+
b0 *
b0 )
0(
0'
b0 &
0%
bx $
0"
b0 !
$end
#5000
b101 >
1%
#10000
0%
#15000
b101 >
1%
#20000
0%
#25000
b101 >
1%
#30000
1'
0%
#35000
b101 >
1%
#40000
b1 C
b100 D
0%
#45000
b101 >
1%
#50000
1.
b0 1
b1 *
b1 0
b100 &
b100 -
1+
1(
0%
#55000
b1 !
b1 <
b101 >
1%
#60000
b0 !
b0 <
0.
b10 C
b1000 D
0+
0(
0%
#65000
b101 >
1%
#70000
1.
b1 1
b10 *
b10 0
b1000 &
b1000 -
1+
1(
0%
#75000
b10 !
b10 <
b101 >
1%
#80000
b0 !
b0 <
0.
b11 C
b1100 D
0+
0(
0%
#85000
b101 >
1%
#90000
1.
b10 1
b11 *
b11 0
b1100 &
b1100 -
1+
1(
0%
#95000
b11 !
b11 <
b101 >
1%
#100000
b0 !
b0 <
0.
b1 C
b10000 D
0+
0(
0%
#105000
b101 >
1%
#110000
1.
b11 1
b1 *
b1 0
b10000 &
b10000 -
1+
1(
0%
#115000
b1 !
b1 <
b101 >
1%
#120000
b0 !
b0 <
0.
b11110 C
b10000000000000 D
0+
0(
0%
#125000
b101 >
1%
#130000
b11111111111 1
b11110 *
b11110 0
b10000000000000 &
b10000000000000 -
1+
1(
0%
#135000
b11110 !
b11110 <
b1111 9
b101 >
1%
#140000
b0 C
b1000000000000000000000 D
0+
0(
0%
#145000
b101 >
1%
#150000
b0 !
b0 <
b1111111111111111111 1
b0 *
b0 0
b1000000000000000000000 &
b1000000000000000000000 -
1+
1(
0%
#155000
b101 >
1%
#160000
b1 )
b1 /
0+
0(
0%
#165000
1"
b1 7
b1 8
b1 ;
b101 >
1%
#170000
0%
#175000
b101 >
1%
#180000
b1 ?
b1 @
b1 A
0%
#185000
b101 >
1%
#190000
b1 !
b1 <
b10000000000000000000 1
b1000000000000000000100 &
b1000000000000000000100 -
1(
0%
#191000
b1 B
#195000
b0 !
b0 <
b0 8
0"
b0 7
b1 :
b0 ;
b101 >
1%
#200000
b10 A
b1 $
0(
0%
#205000
b101 >
1%
#210000
b1 C
b1000000000000000000100 D
b0 ?
b0 @
b11 A
0%
#215000
b101 >
1%
#220000
b1 *
b1 0
1+
1(
0%
#225000
b0 :
b101 >
1%
#230000
b0 )
b0 /
0+
0(
0%
#235000
b101 >
1%
#240000
b11 )
b11 /
0%
#245000
b10 !
b10 <
1"
b10 7
b10 8
b11 ;
b101 >
1%
#250000
0%
#255000
b101 >
1%
#260000
0%
#265000
b101 >
1%
#270000
1(
0%
#271000
b10 B
#275000
b1 !
b1 <
b1 8
1"
b1 7
b10 :
b1 ;
b101 >
1%
#280000
b10 ?
b10 @
b100 A
b10 $
0(
0%
#285000
b101 >
1%
#290000
0%
#295000
b101 >
1%
#300000
1(
0%
#301000
b1 B
#305000
b0 !
b0 <
b0 8
0"
b0 7
b11 :
b0 ;
b101 >
1%
#310000
b10 C
b1 ?
b1 @
b101 A
b1 $
0(
0%
#315000
b101 >
1%
#320000
b10 *
b10 0
1+
1(
0%
#325000
b1 :
b101 >
1%
#330000
b1 C
0+
0(
0%
#335000
b10 !
b10 <
1"
b10 7
b10 8
b10 ;
b101 >
1%
#340000
b1 *
b1 0
1+
1(
0%
#345000
b0 :
b101 >
1%
#350000
b0 )
b0 /
0+
0(
0%
#355000
b101 >
1%
#360000
b10 C
b1000000000000000000000 D
0%
#365000
b101 >
1%
#370000
b0 !
b0 <
b1111111111111111111 1
b10 *
b10 0
b1000000000000000000000 &
b1000000000000000000000 -
1+
1(
0%
#375000
b10 !
b10 <
b0 8
0"
b0 7
b10 =
b101 >
1%
#380000
b1 )
b1 /
0+
0(
0%
#385000
b10 !
b10 <
b11 ;
b101 >
1%
#390000
0%
#395000
b101 >
1%
#400000
b100 )
b100 /
b0 ?
b0 @
b110 A
0%
#405000
b10 !
b10 <
1"
b11 7
b11 8
b111 ;
b101 >
1%
#410000
0%
#415000
b101 >
1%
#420000
b1 ?
b1 @
b111 A
0%
#425000
b101 >
1%
#430000
b11 !
b11 <
b10000000000000000000 1
b1000000000000000000100 &
b1000000000000000000100 -
1(
0%
#431000
b11 B
#435000
b0 !
b0 <
b0 8
0"
b0 7
b100 :
b11 ;
b101 >
1%
#440000
b11 ?
b11 @
b1000 A
b11 $
0(
0%
